riddance/__init__.py
riddance/__main__.py
riddance/cli.py
riddance/identifiers.py
riddance/options.py
riddance/utils.py
riddance/fedora/__init__.py
riddance/fedora/core.py
riddance/fedora/options.py
riddance/fedora/packages.py
riddance/fedora/privacy.py
riddance/fedora/utils.py
riddance/os/__init__.py
riddance/os/fedora.py
riddance/sys/__init__.py
riddance/sys/linux.py
riddance-1.3.0.dist-info/METADATA
riddance-1.3.0.dist-info/WHEEL
riddance-1.3.0.dist-info/licenses/COPYING
riddance-1.3.0.dist-info/RECORD
